agentic_profile_auth/__init__.py
agentic_profile_auth/b64u.py
agentic_profile_auth/did_core_types.py
agentic_profile_auth/did_resolver.py
agentic_profile_auth/ed25519.py
agentic_profile_auth/models.py
agentic_profile_auth/server_authentication.py
agentic_profile_auth/web_did_resolver.py
agentic_profile_auth-0.1.6.dist-info/LICENSE
agentic_profile_auth-0.1.6.dist-info/METADATA
agentic_profile_auth-0.1.6.dist-info/WHEEL
agentic_profile_auth-0.1.6.dist-info/top_level.txt
agentic_profile_auth-0.1.6.dist-info/RECORD
